sphinx_sql/__init__.py
sphinx_sql/sphinx_sql.py
sphinx_sql-1.3.5.dist-info/LICENSE
sphinx_sql-1.3.5.dist-info/METADATA
sphinx_sql-1.3.5.dist-info/WHEEL
sphinx_sql-1.3.5.dist-info/top_level.txt
sphinx_sql-1.3.5.dist-info/RECORD
