Metadata-Version: 2.1
Name: sphinx-sql
Version: 1.3.5
Summary: Sphinx extension for autodoc of SQL files.
Home-page: https://github.com/jackscodemonkey/sphinx-sql
Author: Marcus Robb
License: MIT
License-File: LICENSE
Requires-Dist: ddlparse
Requires-Dist: pytest
Requires-Dist: sphinx
Requires-Dist: sphinx-rtd-theme
